tchat.py
TerminalChat-0.1.7.dist-info/LICENSE
TerminalChat-0.1.7.dist-info/METADATA
TerminalChat-0.1.7.dist-info/WHEEL
TerminalChat-0.1.7.dist-info/entry_points.txt
TerminalChat-0.1.7.dist-info/top_level.txt
TerminalChat-0.1.7.dist-info/RECORD
