Metadata-Version: 2.1
Name: TerminalChat
Version: 0.1.7
Summary: Terminal chat application
Home-page: https://github.com/noah-solomon/terminal-chat
Author: Noah Solomon
Author-email: hello@noahsolo.com
License: MIT License
Requires-Python: >=3.7
License-File: LICENSE
Requires-Dist: certifi (==2022.12.7)
Requires-Dist: charset-normalizer (==3.0.1)
Requires-Dist: click (==8.1.3)
Requires-Dist: idna (==3.4)
Requires-Dist: pytz (==2022.7.1)
Requires-Dist: pytz-deprecation-shim (==0.1.0.post0)
Requires-Dist: requests (==2.28.2)
Requires-Dist: tzdata (==2022.7)
Requires-Dist: tzlocal (==4.2)
Requires-Dist: urllib3 (==1.26.14)
